<?xml version="1.0" encoding="utf-8" ?>
<Buildings>


  <ThingDef Name="BuildingBase" Abstract="True">
    <category>Building</category>
    <thingClass>Building</thingClass>
    <soundImpactDefault>BulletImpactMetal</soundImpactDefault>
    <selectable>true</selectable>
    <drawerType>MapMeshAndRealTime</drawerType>
    <terrainAffordanceNeeded>Light</terrainAffordanceNeeded>
    <repairEffect>Repair</repairEffect>
    <leaveResourcesWhenKilled>true</leaveResourcesWhenKilled>
    <filthLeaving>BuildingRubble</filthLeaving>
  </ThingDef>

  <!--============================== Storage ===========================-->

  <ExtendedStorage.ESdef ParentName="BuildingBase">
    <defName>Storage_Basket</defName>
    <label>Food Basket</label>
    <thingClass>ExtendedStorage.Building_ExtendedStorage</thingClass>
    <graphicData>
      <texPath>Things/Building/Furniture/Basket/Basket</texPath>
      <graphicClass>Graphic_Multi</graphicClass>
      <drawSize>(4,3)</drawSize>
    </graphicData>
    <maxStorage>500</maxStorage>
    <altitudeLayer>Building</altitudeLayer>
    <passability>PassThroughOnly</passability>
    <castEdgeShadows>true</castEdgeShadows>
    <statBases>
      <MaxHitPoints>100</MaxHitPoints>
      <WorkToBuild>580</WorkToBuild>
      <Flammability>1.0</Flammability>
      <Beauty>8</Beauty>
    </statBases>
    <description>Haulers carry raw food and plant matter here for storage.</description>
    <size>(2,1)</size>
    <stuffCategories>
      <li>Metallic</li>
      <li>Woody</li>
    </stuffCategories>
    <costStuffCount>15</costStuffCount>
    <killedLeavings>
      <ChunkSlagSteel>1</ChunkSlagSteel>
    </killedLeavings>
    <filthLeaving>BuildingRubble</filthLeaving>
    <building>
      <fixedStorageSettings>
        <priority>Important</priority>
        <filter>
          <categories>
            <li>FoodRaw</li>
            <li>PlantMatter</li>
            <li>Drugs</li>
          </categories>
          <thingDefs>
            <li>HerbalMedicine</li>
            <li>Pemmican</li>
            <li>Kibble</li>
          </thingDefs>
        </filter>
      </fixedStorageSettings>
    </building>
    <inspectorTabs>
      <li>ITab_Storage</li>
    </inspectorTabs>
    <tickerType>Normal</tickerType>
    <designationCategory>Furniture</designationCategory>
    <staticSunShadowHeight>0.5</staticSunShadowHeight>
    <surfaceType>Item</surfaceType>
    <minifiedDef>MinifiedFurniture</minifiedDef>
    <tradeTags>
      <li>Furniture</li>
    </tradeTags>
  </ExtendedStorage.ESdef>

</Buildings>